README.md
setup.py
nmf/__init__.py
nmf/nmf.py
nmf.egg-info/PKG-INFO
nmf.egg-info/SOURCES.txt
nmf.egg-info/dependency_links.txt
nmf.egg-info/requires.txt
nmf.egg-info/top_level.txt