Metadata-Version: 1.0
Name: nmf
Version: 0.0.1
Summary: Non-negative matrix factorization for building topic models in Python
Home-page: https://github.com/duhaime/nmf
Author: Douglas Duhaime
Author-email: douglas.duhaime@gmail.com
License: MIT
Keywords: data-mining,text-mining,topic-modeling,nmf
Platform: UNKNOWN
